python_commandline/__init__.py
python_commandline/cli.py
python_commandline-0.1.7.dist-info/LICENSE
python_commandline-0.1.7.dist-info/METADATA
python_commandline-0.1.7.dist-info/WHEEL
python_commandline-0.1.7.dist-info/entry_points.txt
python_commandline-0.1.7.dist-info/RECORD
