Metadata-Version: 2.1
Name: python-commandline
Version: 0.1.7
Summary: A set of common Linux commands implementation in Python
Author: jacky.wu
Author-email: jacky.wucheng@gmail.com
Requires-Python: >=3.10,<4.0
Classifier: Programming Language :: Python :: 3
Classifier: Programming Language :: Python :: 3.10
Classifier: Programming Language :: Python :: 3.11
Classifier: Programming Language :: Python :: 3.12
Requires-Dist: fire (>=0.6.0,<0.7.0)
Requires-Dist: pydantic (>=2.10.3,<3.0.0)
Requires-Dist: python-dotenv (>=1.0.1,<2.0.0)
